DA4RDM_Vis_ProcessBased/Evaluate_Fitness.py
DA4RDM_Vis_ProcessBased/Extract.py
DA4RDM_Vis_ProcessBased/Visualize.py
DA4RDM_Vis_ProcessBased/__init__.py
DA4RDM_Vis_ProcessBased/PhaseData/Access.csv
DA4RDM_Vis_ProcessBased/PhaseData/Analysis.csv
DA4RDM_Vis_ProcessBased/PhaseData/Archival.csv
DA4RDM_Vis_ProcessBased/PhaseData/Planning.csv
DA4RDM_Vis_ProcessBased/PhaseData/Production.csv
DA4RDM_Vis_ProcessBased/PhaseData/Reuse.csv
DA4RDM_Vis_ProcessBased-0.1.8.dist-info/LICENSE
DA4RDM_Vis_ProcessBased-0.1.8.dist-info/METADATA
DA4RDM_Vis_ProcessBased-0.1.8.dist-info/WHEEL
DA4RDM_Vis_ProcessBased-0.1.8.dist-info/top_level.txt
DA4RDM_Vis_ProcessBased-0.1.8.dist-info/RECORD
